CHANGELOG.rst
LICENSE.txt
MANIFEST.in
README.rst
setup.py
tms.py
tms.egg-info/PKG-INFO
tms.egg-info/SOURCES.txt
tms.egg-info/dependency_links.txt
tms.egg-info/not-zip-safe
tms.egg-info/top_level.txt