Metadata-Version: 1.1
Name: tms
Version: 0.1.1
Summary: Test match special: fuzzy value matching for test assertions
Home-page: UNKNOWN
Author: Oliver Cope
Author-email: oliver@redgecko.org
License: BSD
Platform: UNKNOWN
Classifier: License :: OSI Approved :: BSD License
Classifier: Topic :: Software Development :: Testing
Classifier: Programming Language :: Python :: 2.6
Classifier: Programming Language :: Python :: 2.7
Classifier: Programming Language :: Python :: 3.2
Classifier: Programming Language :: Python :: 3.3
